goodtables_pandas/__init__.py
goodtables_pandas/check.py
goodtables_pandas/errors.py
goodtables_pandas/json.py
goodtables_pandas/options.py
goodtables_pandas/parse.py
goodtables_pandas/read.py
goodtables_pandas/validate.py
goodtables_pandas_py-0.1.2.dist-info/LICENSE.txt
goodtables_pandas_py-0.1.2.dist-info/WHEEL
goodtables_pandas_py-0.1.2.dist-info/METADATA
goodtables_pandas_py-0.1.2.dist-info/RECORD
