Metadata-Version: 2.1
Name: goodtables-pandas-py
Version: 0.1.2
Summary: Read and validate Frictionless Data Tabular Data Packages with pandas.
Home-page: https://github.com/ezwelty/goodtables-pandas-py
License: MIT
Keywords: frictionless,goodtables,datapackage,pandas
Author: Ethan Welty
Author-email: ethan.welty@gmail.com
Requires-Python: >=3.6,<4.0
Classifier: Development Status :: 3 - Alpha
Classifier: Intended Audience :: Developers
Classifier: Intended Audience :: Information Technology
Classifier: Intended Audience :: Science/Research
Classifier: License :: OSI Approved :: MIT License
Classifier: Operating System :: OS Independent
Classifier: Programming Language :: Python
Classifier: Programming Language :: Python :: 3
Classifier: Programming Language :: Python :: 3.6
Classifier: Programming Language :: Python :: 3.7
Classifier: Programming Language :: Python :: 3.8
Classifier: Programming Language :: Python :: 3.9
Classifier: Topic :: Software Development :: Libraries :: Python Modules
Classifier: Topic :: Software Development :: Testing
Requires-Dist: datapackage (>=1.9.2,<2.0.0)
Requires-Dist: goodtables (>=2.2.1,<3.0.0)
Requires-Dist: pandas (>=1.1.3,<2.0.0)
Requires-Dist: typing-extensions (>=3.7.4,<4.0.0)
Project-URL: Repository, https://github.com/ezwelty/goodtables-pandas-py
